<?xml version="1.0" ?>
<Model Name="GFA_TIEFighter_Pose">
	<Parameter Name="RescaleFactor">0.01</Parameter>
	<Parameter Name="RotationY">180</Parameter>
	<MaterialRef Name="Arms"/>
	<MaterialRef Name="Astronaut_head"/>
	<MaterialRef Name="Backpack"/>
	<MaterialRef Name="Boots"/>
	<MaterialRef Name="Cloth"/>
	<MaterialRef Name="Gear"/>
	<MaterialRef Name="Head"/>
	<MaterialRef Name="Headlight"/>
	<MaterialRef Name="LeftGlove"/>
	<MaterialRef Name="RightArm"/>
	<MaterialRef Name="RightGlove"/>
	<MaterialRef Name="Spacesuit_hood"/>
	<Material Name="EmissiveSpectrumAtlas">
		<Parameter Name="Technique">MESH</Parameter>
		<Parameter Name="ColorMetalTexture">Textures\Custom\enenra\EmissiveSpectrumAtlas_cm.dds</Parameter>
		<Parameter Name="NormalGlossTexture">Textures\Custom\enenra\EmissiveSpectrumAtlas_ng.dds</Parameter>
		<Parameter Name="AddMapsTexture">Textures\Custom\enenra\EmissiveSpectrumAtlas_add.dds</Parameter>
	</Material>
	<Material Name="TIESolarPanels">
		<Parameter Name="Technique">MESH</Parameter>
		<Parameter Name="ColorMetalTexture">Textures\Custom\GFA\TIESolarPanels_cm.dds</Parameter>
		<Parameter Name="NormalGlossTexture">Textures\Models\Cubes\HydrogenThrusterConePlates_ng.dds</Parameter>
	</Material>
	<MaterialRef Name="Emissive"/>
	<MaterialRef Name="Chrome"/>
	<MaterialRef Name="PaintedMetal_Colorable"/>
	<MaterialRef Name="PaintedMetal_Darker"/>
	<MaterialRef Name="PaintedMetal_VeryDark"/>
	<MaterialRef Name="Atlas4_Chrome"/>
	<MaterialRef Name="BlackMetal"/>
	<MaterialRef Name="HydrogenThrusterConePlates"/>
	<MaterialRef Name="Atlas3_Darker"/>
	<MaterialRef Name="Atlas3_Colorable"/>
	<MaterialRef Name="PanelingColorable"/>
	<MaterialRef Name="Atlas3_Chrome"/>
	<MaterialRef Name="HydrogenThrusterInjector"/>
	<MaterialRef Name="GlassInside"/>
	<MaterialRef Name="Conveyor"/>
	<MaterialRef Name="BlackMattePlastic"/>
	<MaterialRef Name="ContractsScreen_01"/>
	<MaterialRef Name="PanelingDarker"/>
	<MaterialRef Name="FabricBlack"/>
	<MaterialRef Name="PaintedMetal_Red"/>
	<MaterialRef Name="Decals"/>
	<MaterialRef Name="CockpitScreen_02"/>
	<MaterialRef Name="CockpitScreen_01"/>
	<MaterialRef Name="CockpitScreen_03"/>
	<MaterialRef Name="MetalMilitary"/>
	<MaterialRef Name="Metal_Dull"/>
	<MaterialRef Name="CockpitScreen_04"/>
	<MaterialRef Name="ButtonsAtlas_Colorable"/>
	<MaterialRef Name="ButtonsAtlas_Darker"/>
	<MaterialRef Name="CockpitScreen_05"/>
	<MaterialRef Name="Leather_Dark"/>
	<MaterialRef Name="Atlas1"/>
	<MaterialRef Name="Atlas4_Darker"/>
	<MaterialRef Name="PlasticWhite"/>
	<MaterialRef Name="HydrogenThrusterCone"/>
	<MaterialRef Name="Construction"/>
</Model>
